monaco/__init__.py
monaco/models.py
monaco/widgets.py
squad_django_monaco-1.2.7.dist-info/LICENSE
squad_django_monaco-1.2.7.dist-info/METADATA
squad_django_monaco-1.2.7.dist-info/WHEEL
squad_django_monaco-1.2.7.dist-info/top_level.txt
squad_django_monaco-1.2.7.dist-info/RECORD
