Metadata-Version: 2.1
Name: squad-django-monaco
Version: 1.2.7
Summary: Monaco editor widgets in the Django Admin
Author: Ayush Shanker
License: MIT
Keywords: monaco
Platform: OS Independent
License-File: LICENSE
Requires-Dist: Django<=5.2
